requestspwn/__init__.py
requestspwn/requestspwn.py
requestspwn/data/latest
requestspwn/data/ructf2018
requestspwn/data/ructfe2017
requestspwn/data/ructfe2018
requestspwn-1.0.0.dist-info/LICENSE
requestspwn-1.0.0.dist-info/METADATA
requestspwn-1.0.0.dist-info/WHEEL
requestspwn-1.0.0.dist-info/top_level.txt
requestspwn-1.0.0.dist-info/RECORD
