Metadata-Version: 2.1
Name: requestspwn
Version: 1.0.0
Summary: Drop-in replacement for the requests library with random user agents as default.
Home-page: https://github.com/pietroferretti/requestspwn
Author: Pietro Ferretti
Author-email: me@pietroferretti.com
License: MIT
Project-URL: Source, https://github.com/pietroferretti/requestspwn
Keywords: ctf http
Platform: UNKNOWN
Classifier: Development Status :: 5 - Production/Stable
Classifier: Programming Language :: Python :: 2
Classifier: Programming Language :: Python :: 2.7
Classifier: Programming Language :: Python :: 3
Classifier: Programming Language :: Python :: 3.4
Classifier: Programming Language :: Python :: 3.5
Classifier: Programming Language :: Python :: 3.6
Classifier: Programming Language :: Python :: 3.7
Classifier: License :: OSI Approved :: MIT License
Classifier: Operating System :: OS Independent
Requires-Dist: requests
